adze_modeler/__init__.py
adze_modeler/__main__.py
adze_modeler/agros2d_wrapper.py
adze_modeler/agros_fields.py
adze_modeler/boundaries.py
adze_modeler/doe.py
adze_modeler/femm_wrapper.py
adze_modeler/geometry.py
adze_modeler/gmsh.py
adze_modeler/material.py
adze_modeler/metadata.py
adze_modeler/model.py
adze_modeler/modelpaths.py
adze_modeler/modelpiece.py
adze_modeler/objects.py
adze_modeler/platforms/__init__.py
adze_modeler/platforms/agros2d.py
adze_modeler/platforms/femm.py
adze_modeler/platforms/fenics_electrostatics.py
adze_modeler/platforms/platform.py
adze_modeler/resources/doc_template/docs/images/tutorial.gif
adze_modeler/resources/doc_template/docs/index.md
adze_modeler/resources/doc_template/mkdocs.yml
adze_modeler/resources/model_template/model.py
adze_modeler/resources/model_template/simulation.py
adze_modeler/server.py
adze_modeler/simulation.py
adze_modeler/snapshot.py
adze_modeler/utils.py
adze_modeler-0.0.1.dist-info/LICENSE
adze_modeler-0.0.1.dist-info/WHEEL
adze_modeler-0.0.1.dist-info/METADATA
adze_modeler-0.0.1.dist-info/RECORD
