Metadata-Version: 2.1
Name: adze-modeler
Version: 0.0.1
Summary: Creates an encapsulated FEM simulation
License: AGPL
Author: Tamas Orosz
Author-email: orosz.tamas@montana.hu
Requires-Python: >=3.8,<3.10
Classifier: License :: Other/Proprietary License
Classifier: Programming Language :: Python :: 3
Classifier: Programming Language :: Python :: 3.8
Classifier: Programming Language :: Python :: 3.9
Requires-Dist: Jinja2 (>=3.0.1,<4.0.0)
Requires-Dist: aiofiles (>=0.7.0,<0.8.0)
Requires-Dist: ezdxf (>=0.16.5,<0.17.0)
Requires-Dist: fastapi (>=0.70,<0.71)
Requires-Dist: gitlint
Requires-Dist: gmsh (>=4.8.4,<5.0.0)
Requires-Dist: importlib-resources (>=5.4.0,<6.0.0)
Requires-Dist: mkdocs (>=1.2.3,<2.0.0)
Requires-Dist: mkdocs-git-revision-date-plugin (>=0.3.1,<0.4.0)
Requires-Dist: mkdocs-material (>=7.3.6,<8.0.0)
Requires-Dist: mkdocstrings (>=0.16.2,<0.17.0)
Requires-Dist: networkx (>=2.6.3,<3.0.0)
Requires-Dist: numpy (>=1.21.0,<2.0.0)
Requires-Dist: pydantic (>=1.8.2,<2.0.0)
Requires-Dist: pygmsh (>=7.1.13,<8.0.0)
Requires-Dist: pyvista (>=0.32.1,<0.33.0)
Requires-Dist: scipy (>=1.7.0,<2.0.0)
Requires-Dist: svgpathtools (>=1.4.2,<2.0.0)
Requires-Dist: uvicorn (>=0.15.0,<0.16.0)
Requires-Dist: vedo (>=2021,<2022)
